ujsondiff/BUILD
ujsondiff/__init__.py
ujsondiff/symbols.py
ujsondiff-3.0.1.dist-info/LICENSE
ujsondiff-3.0.1.dist-info/WHEEL
ujsondiff-3.0.1.dist-info/METADATA
ujsondiff-3.0.1.dist-info/RECORD
