Metadata-Version: 2.1
Name: ujsondiff
Version: 3.0.1
Summary: Diff JSON and JSON-like structures in Python
Home-page: https://github.com/CrispyCrafter/ujsondiff
License: MIT
Keywords: json,diff,diffing,difference,patch,delta,dict,LCS,micropython
Author: BP Greyling
Author-email: bpgreyling@gmail.com
Requires-Python: >=3.8,<4.0
Classifier: Development Status :: 1 - Planning
Classifier: Intended Audience :: Developers
Classifier: License :: OSI Approved :: MIT License
Classifier: Programming Language :: Python :: 3
Classifier: Programming Language :: Python :: 3.8
Classifier: Programming Language :: Python :: 3.9
Classifier: Programming Language :: Python :: 3.10
Classifier: Programming Language :: Python :: 3.11
Classifier: Programming Language :: Python :: 3
Classifier: Programming Language :: Python :: Implementation :: MicroPython
Classifier: Topic :: Software Development :: Libraries :: Python Modules
Project-URL: Repository, https://github.com/CrispyCrafter/ujsondiff
